README.rst
setup.py
mulpy/ThreadingPool.py
mulpy/__init__.py
mulpy.egg-info/PKG-INFO
mulpy.egg-info/SOURCES.txt
mulpy.egg-info/dependency_links.txt
mulpy.egg-info/top_level.txt